odoo/addons/account_payment_mode/README.rst
odoo/addons/account_payment_mode/__init__.py
odoo/addons/account_payment_mode/__manifest__.py
odoo/addons/account_payment_mode/demo/payment_demo.xml
odoo/addons/account_payment_mode/i18n/am.po
odoo/addons/account_payment_mode/i18n/ca.po
odoo/addons/account_payment_mode/i18n/da_DK.po
odoo/addons/account_payment_mode/i18n/de.po
odoo/addons/account_payment_mode/i18n/el_GR.po
odoo/addons/account_payment_mode/i18n/es.po
odoo/addons/account_payment_mode/i18n/es_ES.po
odoo/addons/account_payment_mode/i18n/fi.po
odoo/addons/account_payment_mode/i18n/fr.po
odoo/addons/account_payment_mode/i18n/gl.po
odoo/addons/account_payment_mode/i18n/hr.po
odoo/addons/account_payment_mode/i18n/it.po
odoo/addons/account_payment_mode/i18n/nb_NO.po
odoo/addons/account_payment_mode/i18n/nl.po
odoo/addons/account_payment_mode/i18n/pt.po
odoo/addons/account_payment_mode/i18n/pt_BR.po
odoo/addons/account_payment_mode/i18n/pt_PT.po
odoo/addons/account_payment_mode/i18n/sl.po
odoo/addons/account_payment_mode/i18n/tr.po
odoo/addons/account_payment_mode/migrations/11.0.1.0.1/pre-migration.py
odoo/addons/account_payment_mode/models/__init__.py
odoo/addons/account_payment_mode/models/account_journal.py
odoo/addons/account_payment_mode/models/account_payment_method.py
odoo/addons/account_payment_mode/models/account_payment_mode.py
odoo/addons/account_payment_mode/models/res_partner_bank.py
odoo/addons/account_payment_mode/security/account_payment_mode.xml
odoo/addons/account_payment_mode/security/ir.model.access.csv
odoo/addons/account_payment_mode/static/description/icon.png
odoo/addons/account_payment_mode/tests/__init__.py
odoo/addons/account_payment_mode/tests/test_account_payment_mode.py
odoo/addons/account_payment_mode/views/account_journal.xml
odoo/addons/account_payment_mode/views/account_payment_method.xml
odoo/addons/account_payment_mode/views/account_payment_mode.xml
odoo11_addon_account_payment_mode-11.0.1.0.1.dist-info/DESCRIPTION.rst
odoo11_addon_account_payment_mode-11.0.1.0.1.dist-info/METADATA
odoo11_addon_account_payment_mode-11.0.1.0.1.dist-info/RECORD
odoo11_addon_account_payment_mode-11.0.1.0.1.dist-info/WHEEL
odoo11_addon_account_payment_mode-11.0.1.0.1.dist-info/metadata.json
odoo11_addon_account_payment_mode-11.0.1.0.1.dist-info/top_level.txt
